gitwhodid/__init__.py
gitwhodid/__main__.py
gitwhodid/blame.py
gitwhodid/cli.py
gitwhodid/types.py
gitwhodid/utils.py
gitwhodid-0.1.1.dist-info/WHEEL
gitwhodid-0.1.1.dist-info/entry_points.txt
gitwhodid-0.1.1.dist-info/METADATA
gitwhodid-0.1.1.dist-info/RECORD
