Metadata-Version: 2.3
Name: gitwhodid
Version: 0.1.1
Summary: Who did that? A CLI to reveal Git history by file.
Author: stabldev
Author-email: stabldev <thestabldev@gmail.com>
Requires-Dist: click>=8.2.1
Requires-Dist: rich>=14.1.0
Requires-Python: >=3.13
